audio_classification_features/__init__.py
audio_classification_features/audio_feature_extractor.py
audio_classification_features-2.0.dist-info/LICENSE
audio_classification_features-2.0.dist-info/METADATA
audio_classification_features-2.0.dist-info/WHEEL
audio_classification_features-2.0.dist-info/top_level.txt
audio_classification_features-2.0.dist-info/RECORD
