Metadata-Version: 2.1
Name: audio-classification-features
Version: 2.0
Summary: Complete Package for Audio Classification
Home-page: https://github.com/Sumit189/Audio-Classification-Using-CNN
Author: Sumit Paul
Author-email: sumit.18.paul@gmail.com
License: UNKNOWN
Keywords: ML,audio-classification,audio-features
Platform: UNKNOWN
Classifier: Programming Language :: Python :: 3
Classifier: License :: OSI Approved :: GNU General Public License v3 (GPLv3)
Classifier: Operating System :: OS Independent
Requires-Python: >=3.6
Requires-Dist: pandas
Requires-Dist: numpy
Requires-Dist: tqdm
Requires-Dist: scipy
Requires-Dist: librosa
Requires-Dist: keras
Requires-Dist: python-speech-features
